mekpie/__init__.py
mekpie/__main__.py
mekpie/arguments.py
mekpie/cache.py
mekpie/cc_avr_gcc.py
mekpie/cc_emscripten.py
mekpie/cc_gcc_clang.py
mekpie/cli.py
mekpie/compiler.py
mekpie/config.py
mekpie/core.py
mekpie/create.py
mekpie/debug.py
mekpie/definitions.py
mekpie/messages.py
mekpie/record.py
mekpie/runner.py
mekpie/structure.py
mekpie/util.py
mekpie-0.1.11.dist-info/LICENSE
mekpie-0.1.11.dist-info/METADATA
mekpie-0.1.11.dist-info/WHEEL
mekpie-0.1.11.dist-info/entry_points.txt
mekpie-0.1.11.dist-info/top_level.txt
mekpie-0.1.11.dist-info/RECORD
