Metadata-Version: 2.1
Name: mekpie
Version: 0.1.11
Summary: Make Building C as Simple as Pie
Home-page: https://ejrbuss.net/mekpie/
Author: Eric Buss
Author-email: root@ejrbuss.net
License: MIT
Keywords: c development build pie
Platform: UNKNOWN
Classifier: Development Status :: 3 - Alpha
Classifier: Intended Audience :: Developers
Classifier: Topic :: Software Development :: Build Tools
Classifier: License :: OSI Approved :: MIT License
Classifier: Programming Language :: Python :: 3.6
Requires-Dist: prompt-toolkit
Provides-Extra: dev
Provides-Extra: test
